{
  "generator-water": {
    "hasSonarqubeIntegration": true,
    "applicationTypeEntity": true,
    "applicationType": "entity",
    "projectSuffix": "sharedEntity",
    "projectSuffixUpperCase": "SharedEntity",
    "projectSuffixLowerCase": "sharedentity",
    "projectName": "SharedEntity",
    "projectGroupId": "it.water.shared.entity",
    "projectVersion": "3.0.0",
    "projectTechnology": "water",
    "hasRestServices": true,
    "restContextRoot": "/entities/shared",
    "hasModel": true,
    "isProtectedEntity": true,
    "isOwnedEntity": false,
    "persistenceLib": "jakarta",
    "validationLib": "jakarta",
    "projectPath": "SharedEntity",
    "projectApiPath": "SharedEntity/SharedEntity-api",
    "projectModelPath": "SharedEntity/SharedEntity-model",
    "projectServicePath": "SharedEntity/SharedEntity-service",
    "projectParentPath": "SharedEntity",
    "projectBasePath": "/src/main/java/it/water/shared/entity",
    "projectTestPath": "/src/test/java/it/water/shared/entity",
    "apiPackagePath": "/src/main/java/it/water/shared/entity/api",
    "apiPackage": "it.water.shared.entity.api",
    "actionsPackagePath": "/src/main/java/it/water/shared/entity/actions",
    "actionsPackage": "it.water.shared.entity.actions",
    "modelPackagePath": "/src/main/java/it/water/shared/entity/model",
    "modelPackage": "it.water.shared.entity.model",
    "repositoryPackagePath": "/src/main/java/it/water/shared/entity/repository",
    "repositoryPackage": "it.water.shared.entity.repository",
    "springRepository": false,
    "servicePackagePath": "/src/main/java/it/water/shared/entity/service",
    "servicePackage": "it.water.shared.entity.service",
    "serviceRestPackagePath": "/src/main/java/it/water/shared/entity/service/rest",
    "serviceRestPackage": "it.water.shared.entity.service.rest",
    "testPackage": "it.water.shared.entity",
    "publishModule": true,
    "publishRepoName": "public-water-repository",
    "publishRepoUrl": "https://nexus.acsoftware.it/nexus/repository/maven-water/",
    "publishRepoHasCredentials": true,
    "parent-project": true,
    "WaterVersion": "3.0.0",
    "projectsConfiguration": {
      "SharedEntity": {
        "applicationTypeEntity": true,
        "applicationType": "entity",
        "projectSuffix": "sharedEntity",
        "projectSuffixUpperCase": "SharedEntity",
        "projectSuffixLowerCase": "sharedentity",
        "projectName": "SharedEntity",
        "projectGroupId": "it.water.shared.entity",
        "projectVersion": "3.0.0",
        "projectTechnology": "water",
        "hasRestServices": true,
        "restContextRoot": "/entities/shared",
        "hasModel": true,
        "isProtectedEntity": true,
        "isOwnedEntity": false,
        "persistenceLib": "jakarta",
        "validationLib": "jakarta",
        "projectPath": "SharedEntity",
        "projectApiPath": "SharedEntity/SharedEntity-api",
        "projectModelPath": "SharedEntity/SharedEntity-model",
        "projectServicePath": "SharedEntity/SharedEntity-service",
        "projectParentPath": "SharedEntity",
        "projectBasePath": "/src/main/java/it/water/shared/entity",
        "projectTestPath": "/src/test/java/it/water/shared/entity",
        "apiPackagePath": "/src/main/java/it/water/shared/entity/api",
        "apiPackage": "it.water.shared.entity.api",
        "actionsPackagePath": "/src/main/java/it/water/shared/entity/actions",
        "actionsPackage": "it.water.shared.entity.actions",
        "modelPackagePath": "/src/main/java/it/water/shared/entity/model",
        "modelPackage": "it.water.shared.entity.model",
        "repositoryPackagePath": "/src/main/java/it/water/shared/entity/repository",
        "repositoryPackage": "it.water.shared.entity.repository",
        "springRepository": false,
        "servicePackagePath": "/src/main/java/it/water/shared/entity/service",
        "servicePackage": "it.water.shared.entity.service",
        "serviceRestPackagePath": "/src/main/java/it/water/shared/entity/service/rest",
        "serviceRestPackage": "it.water.shared.entity.service.rest",
        "testPackage": "it.water.shared.entity",
        "publishModule": true,
        "publishRepoName": "public-water-repository",
        "publishRepoUrl": "https://nexus.acsoftware.it/nexus/repository/maven-water/",
        "publishRepoHasCredentials": true
      }
    }
  }
}
